odoo/addons/shopinvader_search_engine_product_multi_price/README.rst
odoo/addons/shopinvader_search_engine_product_multi_price/__init__.py
odoo/addons/shopinvader_search_engine_product_multi_price/__manifest__.py
odoo/addons/shopinvader_search_engine_product_multi_price/i18n/shopinvader_search_engine_product_multi_price.pot
odoo/addons/shopinvader_search_engine_product_multi_price/models/__init__.py
odoo/addons/shopinvader_search_engine_product_multi_price/models/product_product.py
odoo/addons/shopinvader_search_engine_product_multi_price/models/se_backend.py
odoo/addons/shopinvader_search_engine_product_multi_price/models/se_index.py
odoo/addons/shopinvader_search_engine_product_multi_price/readme/CONTRIBUTORS.rst
odoo/addons/shopinvader_search_engine_product_multi_price/readme/DESCRIPTION.rst
odoo/addons/shopinvader_search_engine_product_multi_price/readme/USAGE.rst
odoo/addons/shopinvader_search_engine_product_multi_price/schemas/__init__.py
odoo/addons/shopinvader_search_engine_product_multi_price/schemas/product.py
odoo/addons/shopinvader_search_engine_product_multi_price/static/description/index.html
odoo/addons/shopinvader_search_engine_product_multi_price/tests/__init__.py
odoo/addons/shopinvader_search_engine_product_multi_price/tests/test_product_binding.py
odoo/addons/shopinvader_search_engine_product_multi_price/views/se_backend.xml
odoo/addons/shopinvader_search_engine_product_multi_price/views/se_index.xml
odoo_addon_shopinvader_search_engine_product_multi_price-16.0.1.1.0.dist-info/METADATA
odoo_addon_shopinvader_search_engine_product_multi_price-16.0.1.1.0.dist-info/WHEEL
odoo_addon_shopinvader_search_engine_product_multi_price-16.0.1.1.0.dist-info/top_level.txt
odoo_addon_shopinvader_search_engine_product_multi_price-16.0.1.1.0.dist-info/RECORD
